pbx/__init__.py
pbx/main.py
pbx/builder/__init__.py
pbx/builder/compiler.py
pbx/builder/loader.py
pbx/builder/mode_utils.py
pbx/builder/blocks/__init__.py
pbx/builder/blocks/base/__init__.py
pbx/builder/blocks/base/reverse_shell.macos.python.base.short.py
pbx/builder/blocks/persistence/__init__.py
pbx/builder/blocks/persistence/mac_launch_agent.macos.python.persistence.default.py
pbx/builder/blocks/stealth/__init__.py
pbx/builder/blocks/stealth/obfuscate_vars.all.python.stealth.default.py
pbx/builder/utils/__init__.py
pbx/builder/utils/pbx_decrypt.py
pbx-0.0.2.dist-info/licenses/LICENSE
pbx-0.0.2.dist-info/METADATA
pbx-0.0.2.dist-info/WHEEL
pbx-0.0.2.dist-info/entry_points.txt
pbx-0.0.2.dist-info/top_level.txt
pbx-0.0.2.dist-info/RECORD
