Metadata-Version: 2.4
Name: pbx
Version: 0.0.2
Summary: PayloadBuilder X - A modular payload compiler framework
Home-page: https://github.com/diputs-sudo/payloadx
Author: diputs
Author-email: diputs-sudo@proton.me
Classifier: Programming Language :: Python :: 3
Classifier: License :: Other/Proprietary License
Classifier: Operating System :: OS Independent
Requires-Python: >=3.8
License-File: LICENSE
Dynamic: author
Dynamic: author-email
Dynamic: classifier
Dynamic: description
Dynamic: description-content-type
Dynamic: home-page
Dynamic: license-file
Dynamic: requires-python
Dynamic: summary
